notion_df/__init__.py
notion_df/_pandas.py
notion_df/agent.py
notion_df/base.py
notion_df/blocks.py
notion_df/configs.py
notion_df/constants.py
notion_df/utils.py
notion_df/values.py
notion_df_extended-0.1.0.dist-info/LICENSE
notion_df_extended-0.1.0.dist-info/WHEEL
notion_df_extended-0.1.0.dist-info/METADATA
notion_df_extended-0.1.0.dist-info/RECORD
