Metadata-Version: 2.1
Name: notion-df-extended
Version: 0.1.0
Summary: Notion modified to include more recent packages.
License: MIT
Author: Kevin Hill
Author-email: kivo360@gmail.com
Requires-Python: >=3.8,<4.0
Classifier: License :: OSI Approved :: MIT License
Classifier: Programming Language :: Python :: 3
Classifier: Programming Language :: Python :: 3.8
Classifier: Programming Language :: Python :: 3.9
Classifier: Programming Language :: Python :: 3.10
Classifier: Programming Language :: Python :: 3.11
Requires-Dist: notion-client (>=2.0.0,<3.0.0)
Requires-Dist: pandas (>=2.0.2,<3.0.0)
Requires-Dist: pydantic (>=1.10.9,<2.0.0)
